django_synced_seeders-0.4.0.dist-info/licenses/LICENSE
playground/__init__.py
playground/admin.py
playground/models.py
playground/seeders.py
playground/settings.py
playground/urls.py
playground/migrations/0001_initial.py
playground/migrations/__init__.py
seeds/__init__.py
seeds/admin.py
seeds/apps.py
seeds/models.py
seeds/registries.py
seeds/seeders.py
seeds/utils.py
seeds/management/__init__.py
seeds/management/commands/__init__.py
seeds/management/commands/exportseed.py
seeds/management/commands/syncseeds.py
seeds/migrations/0001_initial.py
seeds/migrations/__init__.py
django_synced_seeders-0.4.0.dist-info/METADATA
django_synced_seeders-0.4.0.dist-info/WHEEL
django_synced_seeders-0.4.0.dist-info/top_level.txt
django_synced_seeders-0.4.0.dist-info/RECORD
