Metadata-Version: 2.4
Name: django-synced-seeders
Version: 0.4.0
Summary: An easy-to-use seeder manager to keep seed data in sync across multiple environments.
Author-email: Starscribers <Starscribers@gmail.com>
Project-URL: Homepage, https://github.com/Starscribers/django-synced-seeders
Project-URL: Repository, https://github.com/Starscribers/django-synced-seeders.git
Project-URL: Issues, https://github.com/Starscribers/django-synced-seeders/issues
Project-URL: Documentation, https://django-synced-seeders.readthedocs.io/
Classifier: Development Status :: 4 - Beta
Classifier: Intended Audience :: Developers
Classifier: License :: OSI Approved :: MIT License
Classifier: Operating System :: OS Independent
Classifier: Programming Language :: Python
Classifier: Programming Language :: Python :: 3
Classifier: Programming Language :: Python :: 3.9
Classifier: Programming Language :: Python :: 3.10
Classifier: Programming Language :: Python :: 3.11
Classifier: Programming Language :: Python :: 3.12
Classifier: Topic :: Software Development :: Libraries :: Python Modules
Classifier: Topic :: Utilities
Classifier: Typing :: Typed
Requires-Python: >=3.9
License-File: LICENSE
Requires-Dist: django>=4.2.24
Requires-Dist: django-stubs[compatible-mypy]>=5.1.3
Requires-Dist: django-stubs-ext>=5.1.3
Requires-Dist: requests>=2.32.4
Requires-Dist: types-requests>=2.32.0.20241016
Requires-Dist: slack-sdk>=3.36.0
Requires-Dist: any-registries>=0.2.0
Requires-Dist: django-stub>=0.1
Provides-Extra: dev
Requires-Dist: pytest>=7.0.0; extra == "dev"
Requires-Dist: black>=22.0.0; extra == "dev"
Requires-Dist: isort>=5.10.0; extra == "dev"
Requires-Dist: mypy>=0.950; extra == "dev"
Requires-Dist: flake8>=4.0.0; extra == "dev"
Requires-Dist: pre-commit>=3.0.0; extra == "dev"
Requires-Dist: bandit>=1.7.0; extra == "dev"
Requires-Dist: twine>=4.0.0; extra == "dev"
Requires-Dist: types-setuptools>=68.0.0; extra == "dev"
Provides-Extra: testing
Requires-Dist: pytest>=7.0.0; extra == "testing"
Requires-Dist: pytest-cov>=3.0.0; extra == "testing"
Provides-Extra: docs
Requires-Dist: sphinx>=7.0.0; extra == "docs"
Requires-Dist: sphinx-conestack-theme>=1.0.0; extra == "docs"
Requires-Dist: sphinx-autodoc-typehints>=1.25.0; extra == "docs"
Requires-Dist: myst-parser>=2.0.0; extra == "docs"
Dynamic: license-file
